[
  {
    "image": "",
    "title": "Episode 1",
    "duration": "09:40",
    "host": "Host Name",
    "guest": "Guest Name 1",
    "description": "Short Description of what is being discussed in episode 1"
  },
  {
    "image": "",
    "title": "Episode 2",
    "duration": "12:15",
    "host": "Host Name",
    "guest": "Guest Name 2",
    "description": "Short Description of what is being discussed in episode 2"
  },
  {
    "image": "",
    "title": "Episode 3",
    "duration": "08:30",
    "host": "Host Name",
    "guest": "Guest Name 3",
    "description": "Short Description of what is being discussed in episode 3"
  },
  {
    "image": "",
    "title": "Episode 4",
    "duration": "11:05",
    "host": "Host Name",
    "guest": "Guest Name 4",
    "description": "Short Description of what is being discussed in episode 4"
  }
]
